{
  "objects": [
    {
      "type": "identity",
      "id": "1",
      "properties": {
        "kind": "IDENTITY_KIND_PID",
        "provider": "local",
        "verified": true
      }
    },
    {
      "type": "identity",
      "id": "2",
      "properties": {
        "kind": "IDENTITY_KIND_PID",
        "provider": "local",
        "verified": true
      }
    },
    {
      "type": "identity",
      "id": "3",
      "properties": {
        "kind": "IDENTITY_KIND_PID",
        "provider": "local",
        "verified": true
      }
    },
    {
      "type": "identity",
      "id": "4",
      "properties": {
        "kind": "IDENTITY_KIND_PID",
        "provider": "local",
        "verified": true
      }
    },
    {
      "type": "identity",
      "id": "5",
      "properties": {
        "kind": "IDENTITY_KIND_PID",
        "provider": "local",
        "verified": true
      }
    },
    {
      "type": "identity",
      "id": "6",
      "properties": {
        "kind": "IDENTITY_KIND_PID",
        "provider": "local",
        "verified": true
      }
    },
    {
      "type": "identity",
      "id": "luke@yavin4base.mil",
      "properties": {
        "kind": "IDENTITY_KIND_EMAIL",
        "provider": "local",
        "verified": true
      }
    },
    {
      "type": "identity",
      "id": "leia@yavin4base.mil",
      "properties": {
        "kind": "IDENTITY_KIND_EMAIL",
        "provider": "local",
        "verified": true
      }
    },
    {
      "type": "identity",
      "id": "han@yavin4base.mil",
      "properties": {
        "kind": "IDENTITY_KIND_EMAIL",
        "provider": "local",
        "verified": true
      }
    },
    {
      "type": "identity",
      "id": "r2d2@droids.yavin4base.mil",
      "properties": {
        "kind": "IDENTITY_KIND_EMAIL",
        "provider": "local",
        "verified": true
      }
    },
    {
      "type": "identity",
      "id": "c3po@droids.yavin4base.mil",
      "properties": {
        "kind": "IDENTITY_KIND_EMAIL",
        "provider": "local",
        "verified": true
      }
    },
    {
      "type": "user",
      "id": "luke@yavin4base.mil",
      "properties": {
        "email": "luke@yavin4base.mil",
        "picture": "https://github.com/aserto-demo/gdrive-images/raw/main/luke.jpg",
        "status": "USER_STATUS_ACTIVE"
      }
    },
    {
      "type": "user",
      "id": "leia@yavin4base.mil",
      "properties": {
        "email": "leia@yavin4base.mil",
        "picture": "https://github.com/aserto-demo/gdrive-images/raw/main/leia.jpg",
        "status": "USER_STATUS_ACTIVE"
      }
    },
    {
      "type": "user",
      "id": "han@yavin4base.mil",
      "properties": {
        "email": "han@yavin4base.mil",
        "picture": "https://github.com/aserto-demo/gdrive-images/raw/main/han.jpg",
        "status": "USER_STATUS_ACTIVE"
      }
    },
    {
      "type": "user",
      "id": "r2d2@droids.yavin4base.mil",
      "properties": {
        "email": "r2d2@droids.yavin4base.mil",
        "picture": "https://github.com/aserto-demo/gdrive-images/raw/main/r2d2.jpg",
        "status": "USER_STATUS_ACTIVE"
      }
    },
    {
      "type": "user",
      "id": "r2d2@droids.yavin4base.mil",
      "properties": {
        "email": "c3po@droids.yavin4base.mil",
        "picture": "https://github.com/aserto-demo/gdrive-images/raw/main/c3po.jpg",
        "status": "USER_STATUS_ACTIVE"
      }
    },
    {
      "type": "group",
      "id": "everyone",
      "properties": {}
    },
    {
      "type": "group",
      "id": "strike-team",
      "properties": {}
    },
    {
      "type": "folder",
      "id": "root",
      "properties": {}
    },
    {
      "type": "folder",
      "id": "missions",
      "properties": {}
    },
    {
      "type": "folder",
      "id": "death-star",
      "properties": {}
    },
    {
      "type": "folder",
      "id": "clone-wars",
      "properties": {}
    },
    {
      "type": "folder",
      "id": "general",
      "properties": {}
    },
    {
      "type": "folder",
      "id": "clone-wars",
      "properties": {}
    },
    {
      "type": "document",
      "id": "siteplan.png",
      "properties": {}
    },
    {
      "type": "document",
      "id": "striketeam.xls",
      "properties": {}
    },
    {
      "type": "document",
      "id": "dining-menu.pdf",
      "properties": {}
    },
    {
      "type": "document",
      "id": "rebel-handbook.pdf",
      "properties": {}
    }
  ]
}
